JapaneseTokenizer/__init__.py
JapaneseTokenizer/datamodels.py
JapaneseTokenizer/init_logger.py
JapaneseTokenizer/object_models.py
JapaneseTokenizer/common/__init__.py
JapaneseTokenizer/common/juman_utils.py
JapaneseTokenizer/common/sever_handler.py
JapaneseTokenizer/common/text_preprocess.py
JapaneseTokenizer/common/timeout_handler.py
JapaneseTokenizer/juman_wrapper/__init__.py
JapaneseTokenizer/juman_wrapper/juman_wrapper.py
JapaneseTokenizer/jumanpp_wrapper/__init__.py
JapaneseTokenizer/jumanpp_wrapper/jumanpp_wrapper.py
JapaneseTokenizer/kytea_wrapper/__init__.py
JapaneseTokenizer/kytea_wrapper/kytea_wrapper.py
JapaneseTokenizer/mecab_wrapper/__init__.py
JapaneseTokenizer/mecab_wrapper/mecab_wrapper.py
JapaneseTokenizer-1.6.dist-info/DESCRIPTION.rst
JapaneseTokenizer-1.6.dist-info/METADATA
JapaneseTokenizer-1.6.dist-info/RECORD
JapaneseTokenizer-1.6.dist-info/WHEEL
JapaneseTokenizer-1.6.dist-info/metadata.json
JapaneseTokenizer-1.6.dist-info/top_level.txt
test/__init__.py
test/test_all.py
test/test_filter_python2.py
test/test_filter_python3.py
test/test_juman_wrapper_python2.py
test/test_juman_wrapper_python3.py
test/test_jumanpp_wrapper_python2.py
test/test_jumanpp_wrapper_python3.py
test/test_kytea_wrapper_python2.py
test/test_kytea_wrapper_python3.py
test/test_mecab_wrapper_python2.py
test/test_mecab_wrapper_python3.py
test/common/__init__.py
test/common/test_server_handler.py
