Metadata-Version: 1.0
Name: JapaneseTokenizer
Version: 1.6
Summary: UNKNOWN
Home-page: https://github.com/Kensuke-Mitsuzawa/JapaneseTokenizers
Author: Kensuke Mitsuzawa
Author-email: kensuke.mit@gmail.com
License: MIT
Keywords: MeCab,和布蕪,Juman,Japanese morphological analyzer,NLP,形態素解析,自然言語処理
Platform: UNKNOWN
